source_instagram/__init__.py
source_instagram/api.py
source_instagram/common.py
source_instagram/components.py
source_instagram/manifest.yaml
source_instagram/run.py
source_instagram/source.py
source_instagram/spec.json
source_instagram/streams.py
airbyte_source_instagram-4.1.0.dist-info/METADATA
airbyte_source_instagram-4.1.0.dist-info/WHEEL
airbyte_source_instagram-4.1.0.dist-info/entry_points.txt
airbyte_source_instagram-4.1.0.dist-info/RECORD
