Metadata-Version: 2.3
Name: airbyte-source-instagram
Version: 4.1.0
Summary: Source implementation for Instagram.
License: MIT
Author: Airbyte
Author-email: contact@airbyte.io
Requires-Python: >=3.10,<3.12
Classifier: License :: OSI Approved :: MIT License
Classifier: Programming Language :: Python :: 3
Classifier: Programming Language :: Python :: 3.10
Classifier: Programming Language :: Python :: 3.11
Requires-Dist: airbyte-cdk (>=6,<7)
Requires-Dist: cached-property (==1.5.2)
Requires-Dist: facebook-business (==21.0.5)
Requires-Dist: pendulum (<3.0.0)
Project-URL: Documentation, https://docs.airbyte.com/integrations/sources/instagram
Project-URL: Homepage, https://airbyte.com
Project-URL: Repository, https://github.com/airbytehq/airbyte
